Bootstrap3ZhongwenbanV11/README.md
Bootstrap3ZhongwenbanV11/__init__.py
Bootstrap3ZhongwenbanV11/__main__.py
Bootstrap3ZhongwenbanV11/file.epub
Bootstrap3ZhongwenbanV11/index.html
Bootstrap3ZhongwenbanV11/css/__init__.py
Bootstrap3ZhongwenbanV11/css/annotations.css
Bootstrap3ZhongwenbanV11/css/main.css
Bootstrap3ZhongwenbanV11/css/normalize.css
Bootstrap3ZhongwenbanV11/css/popup.css
Bootstrap3ZhongwenbanV11/font/__init__.py
Bootstrap3ZhongwenbanV11/font/fontello.eot
Bootstrap3ZhongwenbanV11/font/fontello.svg
Bootstrap3ZhongwenbanV11/font/fontello.ttf
Bootstrap3ZhongwenbanV11/font/fontello.woff
Bootstrap3ZhongwenbanV11/img/__init__.py
Bootstrap3ZhongwenbanV11/img/annotator-glyph-sprite.png
Bootstrap3ZhongwenbanV11/img/annotator-icon-sprite.png
Bootstrap3ZhongwenbanV11/img/apple-touch-icon.png
Bootstrap3ZhongwenbanV11/img/cancelfullscreen.png
Bootstrap3ZhongwenbanV11/img/close.png
Bootstrap3ZhongwenbanV11/img/fullscreen.png
Bootstrap3ZhongwenbanV11/img/loader.gif
Bootstrap3ZhongwenbanV11/img/menu-icon.png
Bootstrap3ZhongwenbanV11/img/save.png
Bootstrap3ZhongwenbanV11/img/saved.png
Bootstrap3ZhongwenbanV11/img/settings-s.png
Bootstrap3ZhongwenbanV11/img/settings.png
Bootstrap3ZhongwenbanV11/img/star.png
Bootstrap3ZhongwenbanV11/js/__init__.py
Bootstrap3ZhongwenbanV11/js/epub.js
Bootstrap3ZhongwenbanV11/js/epub.min.js
Bootstrap3ZhongwenbanV11/js/epub.min.map
Bootstrap3ZhongwenbanV11/js/hooks.min.js
Bootstrap3ZhongwenbanV11/js/hooks.min.map
Bootstrap3ZhongwenbanV11/js/reader.js
Bootstrap3ZhongwenbanV11/js/reader.js.map
Bootstrap3ZhongwenbanV11/js/reader.min.js
Bootstrap3ZhongwenbanV11/js/reader.min.map
Bootstrap3ZhongwenbanV11/js/hooks/__init__.py
Bootstrap3ZhongwenbanV11/js/hooks/extensions/__init__.py
Bootstrap3ZhongwenbanV11/js/hooks/extensions/highlight.js
Bootstrap3ZhongwenbanV11/js/libs/__init__.py
Bootstrap3ZhongwenbanV11/js/libs/jquery.min.js
Bootstrap3ZhongwenbanV11/js/libs/localforage.min.js
Bootstrap3ZhongwenbanV11/js/libs/screenfull.js
bootstrap_3_zhongwenban_v1_1-2024.3.1.0.dist-info/METADATA
bootstrap_3_zhongwenban_v1_1-2024.3.1.0.dist-info/WHEEL
bootstrap_3_zhongwenban_v1_1-2024.3.1.0.dist-info/entry_points.txt
bootstrap_3_zhongwenban_v1_1-2024.3.1.0.dist-info/top_level.txt
bootstrap_3_zhongwenban_v1_1-2024.3.1.0.dist-info/RECORD
